wsrpc_aiohttp/__init__.py
wsrpc_aiohttp/py.typed
wsrpc_aiohttp/signal.py
wsrpc_aiohttp/static/.gitkeep
wsrpc_aiohttp/websocket/__init__.py
wsrpc_aiohttp/websocket/abc.py
wsrpc_aiohttp/websocket/client.py
wsrpc_aiohttp/websocket/common.py
wsrpc_aiohttp/websocket/decorators.py
wsrpc_aiohttp/websocket/handler.py
wsrpc_aiohttp/websocket/route.py
wsrpc_aiohttp/websocket/tools.py
wsrpc_aiohttp-4.0.4.dist-info/LICENSE
wsrpc_aiohttp-4.0.4.dist-info/METADATA
wsrpc_aiohttp-4.0.4.dist-info/WHEEL
wsrpc_aiohttp-4.0.4.dist-info/RECORD
