Metadata-Version: 2.3
Name: wsrpc-aiohttp
Version: 4.0.4
Summary: WSRPC is the RPC over WebSocket for aiohttp
License: Apache-2.0
Keywords: wsrpc,websocket,rpc,json-rpc,js,typescript,javascript
Author: Dmitry Orlov
Author-email: me@mosquito.su
Requires-Python: >=3.8,<4.0
Classifier: Intended Audience :: Developers
Classifier: License :: OSI Approved :: Apache Software License
Classifier: Natural Language :: English
Classifier: Operating System :: MacOS
Classifier: Operating System :: Microsoft
Classifier: Operating System :: POSIX
Classifier: Programming Language :: Python
Classifier: Programming Language :: Python :: 3
Classifier: Programming Language :: Python :: 3.8
Classifier: Programming Language :: Python :: 3.9
Classifier: Programming Language :: Python :: 3.10
Classifier: Programming Language :: Python :: 3.11
Classifier: Programming Language :: Python :: 3.12
Classifier: Programming Language :: Python :: 3.13
Classifier: Programming Language :: Python :: Implementation :: CPython
Classifier: Topic :: Internet
Classifier: Topic :: Software Development
Classifier: Topic :: Software Development :: Libraries
Requires-Dist: aiohttp (<4)
Requires-Dist: typing_extensions ; python_version < "3.10"
Requires-Dist: yarl
Project-URL: Documentation, https://wsrpc.readthedocs.io/en/latest/
Project-URL: Homepage, https://github.com/wsrpc/wsrpc-aiohttp
Project-URL: Source, https://github.com/wsrpc/wsrpc-aiohttp
Project-URL: Tracker, https://github.com/wsrpc/wsrpc-aiohttp/issues
